journify/__init__.py
journify/client.py
journify/consumer.py
journify/request.py
journify/utils.py
journify/version.py
journify/test/__init__.py
journify/test/client.py
journify/test/consumer.py
journify/test/module.py
journify/test/request.py
journify/test/utils.py
journify_python_sdk-2.2.5.dist-info/LICENSE
journify_python_sdk-2.2.5.dist-info/METADATA
journify_python_sdk-2.2.5.dist-info/WHEEL
journify_python_sdk-2.2.5.dist-info/top_level.txt
journify_python_sdk-2.2.5.dist-info/RECORD
