Metadata-Version: 2.1
Name: journify-python-sdk
Version: 2.2.5
Summary: The hassle-free way to integrate Journify into any python application.
Home-page: https://github.com/journifyio/journify-python-sdk
Author: Journify
Author-email: integrations@journify.io
Maintainer: Journify
Maintainer-email: integrations@journify.io
License: MIT License
Classifier: Development Status :: 5 - Production/Stable
Classifier: Intended Audience :: Developers
Classifier: License :: OSI Approved :: MIT License
Classifier: Operating System :: OS Independent
Classifier: Programming Language :: Python
Classifier: Programming Language :: Python :: 3.6
Classifier: Programming Language :: Python :: 3.7
Classifier: Programming Language :: Python :: 3.8
Classifier: Programming Language :: Python :: 3.9
Requires-Python: >=3.6.0
License-File: LICENSE
Requires-Dist: requests (~=2.7)
Requires-Dist: monotonic (~=1.5)
Requires-Dist: backoff (~=2.1)
Requires-Dist: python-dateutil (~=2.2)
Requires-Dist: pylint (==2.17.4)
